README
setup.py
twitterlog.py
TwitterLog.egg-info/PKG-INFO
TwitterLog.egg-info/SOURCES.txt
TwitterLog.egg-info/dependency_links.txt
TwitterLog.egg-info/not-zip-safe
TwitterLog.egg-info/requires.txt
TwitterLog.egg-info/top_level.txt