Metadata-Version: 1.0
Name: TwitterLog
Version: 0.6.1
Summary: Implements a logging handler that logs to Twitter
Home-page: http://github.com/mitsuhiko/twitterlog
Author: Armin Ronacher
Author-email: armin.ronacher@active-4.com
License: BSD
Platform: any
Classifier: Development Status :: 4 - Beta
Classifier: Intended Audience :: Developers
Classifier: License :: OSI Approved :: BSD License
Classifier: Operating System :: OS Independent
Classifier: Programming Language :: Python
Classifier: Topic :: Software Development :: Libraries :: Python Modules
